[
	{
		"title": "Heat Viz",
		"description": "Real-time heat map of the top 150 cryptocurrencies.",
		"techUsed": "React",
		"githubLink": "https://github.com/austindflatt/HeatViz",
		"liveLink": "https://crypto-currency-react.vercel.app/",
		"showViewLive": true,
		"featuredProject": true,
		"image": "images/projects/HeatViz.png"
	},
	{
		"title": "GitHub Profile Finder",
		"description": "A crypto currency web app that allows users to track crypto currencies and view a chart of the crypto's price history",
		"techUsed": "React",
		"githubLink": "https://github.com/austindflatt/crypto-currency-react",
		"liveLink": "https://github-profile-finder-puce.vercel.app/",
		"showViewLive": true,
		"featuredProject": true,
		"image": "images/projects/GithubFinder.png"
	}
]